cofense_triage/__init__.py
cofense_triage/errors.py
cofense_triage/filter_params.py
cofense_triage/schema.json
cofense_triage/triage.py
cofense_triage/triage_api_client.py
cofense_triage/models/__init__.py
cofense_triage/models/attachment.py
cofense_triage/models/attachment_payload.py
cofense_triage/models/base_model.py
cofense_triage/models/category.py
cofense_triage/models/cluster.py
cofense_triage/models/header.py
cofense_triage/models/hostname.py
cofense_triage/models/identity_provider.py
cofense_triage/models/one_click.py
cofense_triage/models/operator.py
cofense_triage/models/report.py
cofense_triage/models/reporter.py
cofense_triage/models/response.py
cofense_triage/models/rule.py
cofense_triage/models/threat_indicator.py
cofense_triage/models/url.py
test/__init__.py
test/conftest.py
test/test_report.py
test/test_reporter.py
test/test_threat_indicator.py
test/test_triage.py
test/test_triage_api_client.py
cofense_triage-0.1.0.dist-info/LICENSE
cofense_triage-0.1.0.dist-info/METADATA
cofense_triage-0.1.0.dist-info/WHEEL
cofense_triage-0.1.0.dist-info/top_level.txt
cofense_triage-0.1.0.dist-info/RECORD
