Metadata-Version: 2.1
Name: cofense-triage
Version: 0.1.0
Summary: Python interface to the Cofense Triage API V2
Home-page: https://github.com/cofense/triage-sdk-python
Author: Eddie Lebow
Author-email: oss@cofense.com
Maintainer: Cofense, Inc.
Maintainer-email: oss@cofense.com
License: MIT
Platform: UNKNOWN
Classifier: Development Status :: 5 - Production/Stable
Classifier: Intended Audience :: Developers
Classifier: Intended Audience :: Information Technology
Classifier: Intended Audience :: System Administrators
Classifier: License :: OSI Approved :: MIT License
Classifier: Operating System :: OS Independent
Classifier: Programming Language :: Python
Requires-Dist: requests-oauthlib
Requires-Dist: jsonapi-client
